seccomp.cpython-312-x86_64-linux-gnu.so
mephi42_seccomp-2.5.6.dist-info/METADATA
mephi42_seccomp-2.5.6.dist-info/WHEEL
mephi42_seccomp-2.5.6.dist-info/top_level.txt
mephi42_seccomp-2.5.6.dist-info/RECORD
