Metadata-Version: 2.2
Name: mephi42-seccomp
Version: 2.5.6
Summary: Python binding for libseccomp
Home-page: https://github.com/seccomp/libseccomp
Maintainer: Paul Moore
Maintainer-email: paul@paul-moore.com
License: LGPLv2.1
Platform: Linux
Dynamic: description
Dynamic: home-page
Dynamic: license
Dynamic: maintainer
Dynamic: maintainer-email
Dynamic: platform
Dynamic: summary
